era/__init__.py
era/Assets/refresh-icon.png
era/Database/__init__.py
era/Database/Dao/__init__.py
era/Database/Dao/emailAccountDao.py
era/Database/Dao/emailTemplateDao.py
era/Database/Impl/__init__.py
era/Database/Impl/emailAccountDaoImpl.py
era/Database/Impl/emailTemplateDaoImpl.py
era/Database/Model/__init__.py
era/Database/Model/emailAccountModel.py
era/Database/Model/emailTemplateModel.py
era/Database/Model/recipientModel.py
era/Database/Repository/__init__.py
era/Database/Repository/baseDatabaaseRepository.py
era/Database/Repository/databaseRepository.py
era/Database/Repository/sqliteRepository.py
era/Logger/__init__.py
era/Logger/logger.py
era/Service/__init__.py
era/Service/emailService.py
era/Utility/ConfigUtility.py
era/Utility/FileUtility.py
era/Utility/StringUtilityCTK.py
era/Utility/__init__.py
era/View/__init__.py
era/View/edit_email_list_top_level.py
era/View/edit_template_top_level.py
era/View/main_view.py
src/__init__.py
src/Database/__init__.py
src/Database/Dao/__init__.py
src/Database/Dao/emailAccountDao.py
src/Database/Dao/emailTemplateDao.py
src/Database/Impl/__init__.py
src/Database/Impl/emailAccountDaoImpl.py
src/Database/Impl/emailTemplateDaoImpl.py
src/Database/Model/__init__.py
src/Database/Model/emailAccountModel.py
src/Database/Model/emailTemplateModel.py
src/Database/Repository/__init__.py
src/Database/Repository/baseDatabaaseRepository.py
src/Database/Repository/baseRepository.py
src/Database/Repository/databaseRepository.py
src/Database/Repository/sqliteRepository.py
src/Logger/__init__.py
src/Logger/logger.py
src/Service/__init__.py
src/Service/emailService.py
src/Utility/ConfigUtility.py
src/Utility/StringUtilityCTK.py
src/Utility/__init__.py
src/View/__init__.py
src/View/edit_template_top_level.py
src/View/main_view.py
src/View/testHtml.py
EmailNotice-1.2.5.dist-info/METADATA
EmailNotice-1.2.5.dist-info/WHEEL
EmailNotice-1.2.5.dist-info/top_level.txt
EmailNotice-1.2.5.dist-info/RECORD
