Metadata-Version: 2.1
Name: EmailNotice
Version: 1.2.5
Summary: GUI Application
Home-page: 
Author: HexBee
Author-email: mat230821@hotmail.com
Classifier: Programming Language :: Python :: 3
Classifier: License :: OSI Approved :: MIT License
Classifier: Operating System :: OS Independent
Requires-Python: >=3.5
Requires-Dist: pandas
Requires-Dist: xlsxwriter
Requires-Dist: openpyxl
Requires-Dist: lxml
Requires-Dist: configparser
Requires-Dist: Pillow
Requires-Dist: customtkinter
